friendsbalt/acs/__init__.py
friendsbalt/acs/average_color.py
friendsbalt/acs/avl.py
friendsbalt/acs/bst.py
friendsbalt/acs/diff.py
friendsbalt/acs/graph.py
friendsbalt/acs/huffman.py
friendsbalt/acs/linear_adts.py
friendsbalt/acs/maps.py
friendsbalt/acs/plotter.py
friendsbalt/acs/pq.py
friendsbalt/acs/testavl.py
friendsbalt/acs/uf.py
friendsbalt/acs/vector.py
friendsbalt-0.1.42.dist-info/METADATA
friendsbalt-0.1.42.dist-info/WHEEL
friendsbalt-0.1.42.dist-info/licenses/LICENSE
friendsbalt-0.1.42.dist-info/RECORD
