Metadata-Version: 2.4
Name: friendsbalt
Version: 0.1.42
Summary: Helper code for Friends School of Baltimore CS curriculum
Project-URL: Homepage, https://github.com/yourusername/friendsbaltcs
Project-URL: Bug Tracker, https://github.com/yourusername/friendsbaltcs/issues
Author-email: Joel Hammer <jhammer@friendsbalt.org>
License-File: LICENSE
Classifier: License :: OSI Approved :: MIT License
Classifier: Operating System :: OS Independent
Classifier: Programming Language :: Python :: 3
Requires-Python: >=3.7
Requires-Dist: matplotlib
